[
  {
    "codPrestacion": "03-07-024-00",
    "nombre": "REACCION CUTANEA A ALERGENOS (INC VALOR",
    "grupo": "ALERGIAS",
    "tipoExamen": 1
  },
  {
    "codPrestacion": "03-07-005-01",
    "nombre": "TEST DE PARCHE, HASTA 24",
    "grupo": "ALERGIAS",
    "tipoExamen": 1
  },
  {
    "codPrestacion": "03-91-665-00",
    "nombre": "TEST PROVOCACION CON MEDICA. Y ALIMENTOS",
    "grupo": "ALERGIAS",
    "tipoExamen": 1
  },
  {
    "codPrestacion": "03-91-101-00",
    "nombre": "TEST SUERO AUTOLOGO",
    "grupo": "ALERGIAS",
    "tipoExamen": 1
  },
  {
    "codPrestacion": "18-01-012-00",
    "nombre": "- REFLUJO ACIDO, TEST DE (GROSSMAN O SIM",
    "grupo": "ENDOSCOPICOS",
    "tipoExamen": 7
  },
  {
    "codPrestacion": "18-01-006-00",
    "nombre": "COLONOSCOPIA LARGA INCL SIGMOIDOSCOPIA",
    "grupo": "ENDOSCOPICOS",
    "tipoExamen": 7
  },
  {
    "codPrestacion": "04-04-218-00",
    "nombre": "ELASTOGRAFIA HEPATICA",
    "grupo": "ENDOSCOPICOS",
    "tipoExamen": 6
  },
  {
    "codPrestacion": "18-01-922-00",
    "nombre": "ENDOSONOGRAFIA ALTA CON PUNCION",
    "grupo": "ENDOSCOPICOS",
    "tipoExamen": 7
  },
  {
    "codPrestacion": "18-01-903-00",
    "nombre": "ENDOSONOGRAFIA ALTA SIN PUNCIÓN",
    "grupo": "ENDOSCOPICOS",
    "tipoExamen": 7
  },
  {
    "codPrestacion": "18-01-011-00",
    "nombre": "MANOMETRIA ESOFAGICA",
    "grupo": "ENDOSCOPICOS",
    "tipoExamen": 7
  },
  {
    "codPrestacion": "18-01-001-00",
    "nombre": "PANENDOSCOPIA( HONORARIOS MEDICO)",
    "grupo": "ENDOSCOPICOS",
    "tipoExamen": 7
  },
  {
    "codPrestacion": "18-91-044-00",
    "nombre": "TEST DE AIRE ESPIRADO",
    "grupo": "ENDOSCOPICOS",
    "tipoExamen": 7
  },
  {
    "codPrestacion": "18-01-037-00",
    "nombre": "TEST DE UREASA",
    "grupo": "ENDOSCOPICOS",
    "tipoExamen": 6
  },
  {
    "codPrestacion": "20-01-015-00",
    "nombre": "COLOCACION O EXTRACCION DE DISPOSITIVO",
    "grupo": "GINECOLOGIA",
    "tipoExamen": 7
  },
  {
    "codPrestacion": "11-01-043-00",
    "nombre": "ELECTROENCEFALOGRAMA DIGITAL 32 CANALES",
    "grupo": "NEUROLOGIA",
    "tipoExamen": 7
  },
  {
    "codPrestacion": "11-01-010-01",
    "nombre": "ELECTROMIOGRAFIA",
    "grupo": "NEUROLOGIA",
    "tipoExamen": 7
  },
  {
    "codPrestacion": "11-01-052-00",
    "nombre": "POLISOMNOGRAFÍA BASAL AMBULATORIA",
    "grupo": "NEUROLOGIA",
    "tipoExamen": 7
  },
  {
    "codPrestacion": "11-01-050-00",
    "nombre": "POLISOMNOGRAFÍA BASAL HOSPITALIZADO",
    "grupo": "NEUROLOGIA",
    "tipoExamen": 7
  },
  {
    "codPrestacion": "11-01-051-00",
    "nombre": "POLISOMNOGRAFÍA NOCHE DIVIDIDA",
    "grupo": "NEUROLOGIA",
    "tipoExamen": 7
  },
  {
    "codPrestacion": "11-01-011-01",
    "nombre": "POTENCIALES EVOCADOS SOMASENSORIALES",
    "grupo": "NEUROLOGIA",
    "tipoExamen": 7
  },
  {
    "codPrestacion": "11-01-011-02",
    "nombre": "POTENCIALES EVOCADOS VISUALES",
    "grupo": "NEUROLOGIA",
    "tipoExamen": 7
  },
  {
    "codPrestacion": "11-01-012-00",
    "nombre": "VELOCIDAD DE CONDUCCION",
    "grupo": "NEUROLOGIA",
    "tipoExamen": 7
  },
  {
    "codPrestacion": "11-01-044-01",
    "nombre": "VIDEO EEG MONITOREO DE 4 HRS (AMB)",
    "grupo": "NEUROLOGIA",
    "tipoExamen": 7
  },
  {
    "codPrestacion": "11-01-044-02",
    "nombre": "VIDEO EEG MONITOREO 12 HRS.",
    "grupo": "NEUROLOGIA",
    "tipoExamen": 7
  },
  {
    "codPrestacion": "12-99-003-00",
    "nombre": "AUTORREFRACTOMETRIA",
    "grupo": "OFTALMOLOGIA",
    "tipoExamen": 7
  },
  {
    "codPrestacion": "12-01-042-00",
    "nombre": "CAMPIMETRIA COMP. C/OJO",
    "grupo": "OFTALMOLOGIA",
    "tipoExamen": 7
  },
  {
    "codPrestacion": "12-01-003-00",
    "nombre": "CUANTIFICACION DE LAGRIMACION",
    "grupo": "OFTALMOLOGIA",
    "tipoExamen": 7
  },
  {
    "codPrestacion": "12-01-004-00",
    "nombre": "CURVA DE TENSION APLANATICA.C/OJO.POR C/",
    "grupo": "OFTALMOLOGIA",
    "tipoExamen": 7
  },
  {
    "codPrestacion": "12-01-020-00",
    "nombre": "ECOBIOMETRIA CALCULO LENTE INTRAOCULAR",
    "grupo": "OFTALMOLOGIA",
    "tipoExamen": 7
  },
  {
    "codPrestacion": "04-04-013-00",
    "nombre": "ECOTOMOGRAFIA OCULAR BIDIMENSIONAL",
    "grupo": "OFTALMOLOGIA",
    "tipoExamen": 6
  },
  {
    "codPrestacion": "12-01-009-00",
    "nombre": "EXPLOR. SENS.:ESTRABISMO.EST.COMPLETO.AM",
    "grupo": "OFTALMOLOGIA",
    "tipoExamen": 7
  },
  {
    "codPrestacion": "12-95-001-00",
    "nombre": "PAQUIMETRIA CORNEAL",
    "grupo": "OFTALMOLOGIA",
    "tipoExamen": 7
  },
  {
    "codPrestacion": "12-01-011-00",
    "nombre": "PRUEBAS DE PROVOCACION  GLAUCOMA UNO O A",
    "grupo": "OFTALMOLOGIA",
    "tipoExamen": 7
  },
  {
    "codPrestacion": "12-99-010-01",
    "nombre": "RECUENTO DE CELULAS ENDOTELIALES",
    "grupo": "OFTALMOLOGIA",
    "tipoExamen": 7
  },
  {
    "codPrestacion": "12-01-014-00",
    "nombre": "TONOMETRIA APLANATICA. CADA OJO",
    "grupo": "OFTALMOLOGIA",
    "tipoExamen": 7
  },
  {
    "codPrestacion": "12-01-043-00",
    "nombre": "TOPOGRAFIA CORNEAL CADA OJO",
    "grupo": "OFTALMOLOGIA",
    "tipoExamen": 7
  },
  {
    "codPrestacion": "13-01-021-00",
    "nombre": "AUDIOMETRIA ADULTOS",
    "grupo": "OTORRINOLARINGOLOGIA",
    "tipoExamen": 7
  },
  {
    "codPrestacion": "13-01-021-01",
    "nombre": "AUDIOMETRIA DE ALTA FRECUENCIA",
    "grupo": "OTORRINOLARINGOLOGIA",
    "tipoExamen": 7
  },
  {
    "codPrestacion": "13-01-008-00",
    "nombre": "AUDIOMETRIA NINOS",
    "grupo": "OTORRINOLARINGOLOGIA",
    "tipoExamen": 7
  },
  {
    "codPrestacion": "13-01-011-00",
    "nombre": "AUDIOMETRIA POR POTENCIALES EVOCADOS",
    "grupo": "OTORRINOLARINGOLOGIA",
    "tipoExamen": 7
  },
  {
    "codPrestacion": "13-01-012-00",
    "nombre": "COCLEOVESTIBULAR CON ELECTRONISTAGMOGRAF",
    "grupo": "OTORRINOLARINGOLOGIA",
    "tipoExamen": 7
  },
  {
    "codPrestacion": "13-91-002-00",
    "nombre": "EMISIONES OTOACUSTICAS",
    "grupo": "OTORRINOLARINGOLOGIA",
    "tipoExamen": 7
  },
  {
    "codPrestacion": "13-91-001-00",
    "nombre": "EMISIONES OTOACUSTICAS EN RECIEN NACIDOS",
    "grupo": "OTORRINOLARINGOLOGIA",
    "tipoExamen": 7
  },
  {
    "codPrestacion": "13-01-009-00",
    "nombre": "IMPEDANCIOMETRIA ADULTO-NINO",
    "grupo": "OTORRINOLARINGOLOGIA",
    "tipoExamen": 7
  },
  {
    "codPrestacion": "13-91-008-00",
    "nombre": "MANIOBRAS DE REPOSICION CANALICULAR",
    "grupo": "OTORRINOLARINGOLOGIA",
    "tipoExamen": 7
  },
  {
    "codPrestacion": "13-01-003-01",
    "nombre": "NASOFARINGOLARINGOFIBROSCOPIA INC.H.M.Q",
    "grupo": "OTORRINOLARINGOLOGIA",
    "tipoExamen": 7
  },
  {
    "codPrestacion": "13-01-020-00",
    "nombre": "OCTAVO PAR ADULTOS Y NINOS",
    "grupo": "OTORRINOLARINGOLOGIA",
    "tipoExamen": 7
  },
  {
    "codPrestacion": "13-01-016-00",
    "nombre": "PERMEABILIDAD TUBARIA, ESTUDIO INSTRUMEN",
    "grupo": "OTORRINOLARINGOLOGIA",
    "tipoExamen": 7
  },
  {
    "codPrestacion": "13-01-017-00",
    "nombre": "PRUEBA CALORICA (PROCED. AUTO)",
    "grupo": "OTORRINOLARINGOLOGIA",
    "tipoExamen": 7
  },
  {
    "codPrestacion": "13-01-010-00",
    "nombre": "PRUEBA DE AUDIFONOS",
    "grupo": "OTORRINOLARINGOLOGIA",
    "tipoExamen": 7
  },
  {
    "codPrestacion": "13-91-007-00",
    "nombre": "REHABITUACION VESTIBULAR",
    "grupo": "OTORRINOLARINGOLOGIA",
    "tipoExamen": 7
  },
  {
    "codPrestacion": "13-91-003-00",
    "nombre": "RINOMETRIA ACUSTICA",
    "grupo": "OTORRINOLARINGOLOGIA",
    "tipoExamen": 7
  },
  {
    "codPrestacion": "13-01-019-00",
    "nombre": "TEST DE GLICEROL",
    "grupo": "OTORRINOLARINGOLOGIA",
    "tipoExamen": 7
  },
  {
    "codPrestacion": "13-91-013-00",
    "nombre": "VEMPS",
    "grupo": "OTORRINOLARINGOLOGIA",
    "tipoExamen": 7
  },
  {
    "codPrestacion": "13-91-014-00",
    "nombre": "V-HIT",
    "grupo": "OTORRINOLARINGOLOGIA",
    "tipoExamen": 7
  },
  {
    "codPrestacion": "16-02-201-00",
    "nombre": "BIOPSIA DE PIEL Y/O MUCOSA X CURET O SEC",
    "grupo": "PROCED.CIRUGIA MENOR",
    "tipoExamen": 7
  },
  {
    "codPrestacion": "16-01-115-00",
    "nombre": "IMPLANTES SUBCUTANEOS (NO INCL. DISPOSIT",
    "grupo": "PROCED.CIRUGIA MENOR",
    "tipoExamen": 7
  },
  {
    "codPrestacion": "16-02-231-00",
    "nombre": "ONICECTOMIA TOTAL O PARCIAL SIMPLE",
    "grupo": "PROCED.CIRUGIA MENOR",
    "tipoExamen": 7
  },
  {
    "codPrestacion": "17-07-008-00",
    "nombre": "CAPACIDAD DE DIFUSION, ESTUDIO DE",
    "grupo": "RESPIRATORIOS",
    "tipoExamen": 8
  },
  {
    "codPrestacion": "17-07-011-00",
    "nombre": "CURVA FLUJO  VOLUMEN",
    "grupo": "RESPIRATORIOS",
    "tipoExamen": 8
  },
  {
    "codPrestacion": "17-07-002-00",
    "nombre": "ESPIROMETRIA BASAL CON BRONCODILATADOR",
    "grupo": "RESPIRATORIOS",
    "tipoExamen": 8
  },
  {
    "codPrestacion": "17-07-007-01",
    "nombre": "FENO",
    "grupo": "RESPIRATORIOS",
    "tipoExamen": 8
  },
  {
    "codPrestacion": "17-07-007-04",
    "nombre": "FENO ALVEOLAR",
    "grupo": "RESPIRATORIOS",
    "tipoExamen": 8
  },
  {
    "codPrestacion": "17-07-007-03",
    "nombre": "FENO NASAL",
    "grupo": "RESPIRATORIOS",
    "tipoExamen": 8
  },
  {
    "codPrestacion": "17-07-021-00",
    "nombre": "FIBROBRONCOSCOPIA (LARIGOTRAQUEOSCOPIA)",
    "grupo": "RESPIRATORIOS",
    "tipoExamen": 8
  },
  {
    "codPrestacion": "17-92-008-01",
    "nombre": "IOS OSCILOMETRIA DE IMPULSO",
    "grupo": "RESPIRATORIOS",
    "tipoExamen": 8
  },
  {
    "codPrestacion": "17-07-052-00",
    "nombre": "MONITOREO SATURACION DE O2 DURANTE SUEÑO",
    "grupo": "RESPIRATORIOS",
    "tipoExamen": 8
  },
  {
    "codPrestacion": "17-92-007-01",
    "nombre": "OXIDO NITRICO NASAL- PROGR DCP FONASA",
    "grupo": "RESPIRATORIOS",
    "tipoExamen": 8
  },
  {
    "codPrestacion": "17-07-014-01",
    "nombre": "PIMETRIA",
    "grupo": "RESPIRATORIOS",
    "tipoExamen": 8
  },
  {
    "codPrestacion": "17-07-063-00",
    "nombre": "POLIGRAFIA CARDIORRESP. DEL SUEÑO AMB",
    "grupo": "RESPIRATORIOS",
    "tipoExamen": 8
  },
  {
    "codPrestacion": "17-91-102-00",
    "nombre": "RECUENTO DIFERENCIAL LBA",
    "grupo": "RESPIRATORIOS",
    "tipoExamen": 7
  },
  {
    "codPrestacion": "17-07-055-00",
    "nombre": "SATURACION DE O2 EN REPOSO Y/O EJERCICIO",
    "grupo": "RESPIRATORIOS",
    "tipoExamen": 8
  },
  {
    "codPrestacion": "17-07-018-00",
    "nombre": "TEST DE CAMINATA DE 6 MINUTOS",
    "grupo": "RESPIRATORIOS",
    "tipoExamen": 8
  },
  {
    "codPrestacion": "17-01-003-05",
    "nombre": "TEST DE ESFUERZO CARDIOPULMONAR",
    "grupo": "RESPIRATORIOS",
    "tipoExamen": 7
  },
  {
    "codPrestacion": "17-07-004-00",
    "nombre": "TEST DE PROVOCACION C/EJERCICIO",
    "grupo": "RESPIRATORIOS",
    "tipoExamen": 8
  },
  {
    "codPrestacion": "03-07-007-00",
    "nombre": "TEST DE SUDOR PROCEDIMIENTO UTM",
    "grupo": "RESPIRATORIOS",
    "tipoExamen": 1
  },
  {
    "codPrestacion": "17-07-005-00",
    "nombre": "TEST PROVOCACION CON METACOLINA",
    "grupo": "RESPIRATORIOS",
    "tipoExamen": 8
  },
  {
    "codPrestacion": "17-07-020-00",
    "nombre": "VOLUMEN RESIDUAL, ESTUDIO DE MEDICION DE",
    "grupo": "RESPIRATORIOS",
    "tipoExamen": 8
  },
  {
    "codPrestacion": "04-04-005-01",
    "nombre": "ECOTOMOGRAFIA TRANSRECTAL",
    "grupo": "UROLOGICOS",
    "tipoExamen": 6
  },
  {
    "codPrestacion": "03-08-029-00",
    "nombre": "ESPERMIOGRAMA",
    "grupo": "UROLOGICOS",
    "tipoExamen": 1
  },
  {
    "codPrestacion": "03-91-999-63",
    "nombre": "ESPERMIOGRAMA PARA ESTUDIO DE FERTILIDAD",
    "grupo": "UROLOGICOS",
    "tipoExamen": 1
  },
  {
    "codPrestacion": "19-01-011-01",
    "nombre": "UROFLUJOMETRIA",
    "grupo": "UROLOGICOS",
    "tipoExamen": 7
  },
  {
    "codPrestacion": "44-04-071-00",
    "nombre": "VACUNA  HEPATITIS A (AVAXIM)",
    "grupo": "VACUNAS",
    "tipoExamen": 7
  },
  {
    "codPrestacion": "44-04-087-00",
    "nombre": "VACUNA ANTIRRABICA (VERORAB)",
    "grupo": "VACUNAS",
    "tipoExamen": 7
  },
  {
    "codPrestacion": "44-04-205-00",
    "nombre": "VACUNA DTPA (ADACEL)",
    "grupo": "VACUNAS",
    "tipoExamen": 7
  },
  {
    "codPrestacion": "44-04-206-00",
    "nombre": "VACUNA DTPA (BOOSTRIX)",
    "grupo": "VACUNAS",
    "tipoExamen": 7
  },
  {
    "codPrestacion": "44-04-207-00",
    "nombre": "VACUNA FIEBRE AMARILLA (STAMARIL)",
    "grupo": "VACUNAS",
    "tipoExamen": 7
  },
  {
    "codPrestacion": "44-04-082-00",
    "nombre": "VACUNA FIEBRE TIFOIDEA (TYPHIM)",
    "grupo": "VACUNAS",
    "tipoExamen": 7
  },
  {
    "codPrestacion": "44-04-222-01",
    "nombre": "VACUNA HEPATITIS A ADU (VAQTA 50 )",
    "grupo": "VACUNAS",
    "tipoExamen": 7
  },
  {
    "codPrestacion": "44-04-074-00",
    "nombre": "VACUNA HEPATITIS A (HAVRIX JR)",
    "grupo": "VACUNAS",
    "tipoExamen": 7
  },
  {
    "codPrestacion": "44-04-097-00",
    "nombre": "VACUNA HEPATITIS A PED (AVAXIM PED)",
    "grupo": "VACUNAS",
    "tipoExamen": 7
  },
  {
    "codPrestacion": "44-04-222-00",
    "nombre": "VACUNA HEPATITIS A PED (VAQTA PED)",
    "grupo": "VACUNAS",
    "tipoExamen": 7
  },
  {
    "codPrestacion": "44-04-096-00",
    "nombre": "VACUNA HEPATITIS A Y B (TWINRIX)",
    "grupo": "VACUNAS",
    "tipoExamen": 7
  },
  {
    "codPrestacion": "44-04-073-00",
    "nombre": "VACUNA HEPATITIS B (ENGERIX)",
    "grupo": "VACUNAS",
    "tipoExamen": 7
  },
  {
    "codPrestacion": "44-04-221-01",
    "nombre": "VACUNA HEPATITIS B (HEBERVIOVAC)",
    "grupo": "VACUNAS",
    "tipoExamen": 7
  },
  {
    "codPrestacion": "44-04-223-00",
    "nombre": "VACUNA INFLUENZA PARTICULAR",
    "grupo": "VACUNAS",
    "tipoExamen": 7
  },
  {
    "codPrestacion": "44-04-213-00",
    "nombre": "VACUNA MENINGOCOCICA ACWY (MENVEO)",
    "grupo": "VACUNAS",
    "tipoExamen": 7
  },
  {
    "codPrestacion": "44-04-226-00",
    "nombre": "VACUNA MENINGOCOCICA B (BEXSERO)",
    "grupo": "VACUNAS",
    "tipoExamen": 7
  },
  {
    "codPrestacion": "44-04-126-00",
    "nombre": "VACUNA  MENINGOCOCICA B (TRUMENBA)",
    "grupo": "VACUNAS",
    "tipoExamen": 7
  },
  {
    "codPrestacion": "44-04-216-00",
    "nombre": "VACUNA MENINGOCOCO ACWY (NIMENRIX)",
    "grupo": "VACUNAS",
    "tipoExamen": 7
  },
  {
    "codPrestacion": "44-04-116-00",
    "nombre": "VACUNA MINISTERIAL ANTIRRABICA",
    "grupo": "VACUNAS",
    "tipoExamen": 7
  },
  {
    "codPrestacion": "44-04-117-00",
    "nombre": "VACUNA MINISTERIAL ANTITETÁNICA",
    "grupo": "VACUNAS",
    "tipoExamen": 7
  },
  {
    "codPrestacion": "44-04-225-03",
    "nombre": "VACUNA MINISTERIAL COVID",
    "grupo": "VACUNAS",
    "tipoExamen": 7
  },
  {
    "codPrestacion": "44-04-118-00",
    "nombre": "VACUNA MINISTERIAL DTPA",
    "grupo": "VACUNAS",
    "tipoExamen": 7
  },
  {
    "codPrestacion": "44-04-107-00",
    "nombre": "VACUNA MINISTERIAL HEPATITIS B",
    "grupo": "VACUNAS",
    "tipoExamen": 7
  },
  {
    "codPrestacion": "44-04-108-00",
    "nombre": "VACUNA MINISTERIAL HEXAVALENTE",
    "grupo": "VACUNAS",
    "tipoExamen": 7
  },
  {
    "codPrestacion": "44-04-225-00",
    "nombre": "VACUNA MINISTERIAL INFLUENZA",
    "grupo": "VACUNAS",
    "tipoExamen": 7
  },
  {
    "codPrestacion": "44-04-121-00",
    "nombre": "VACUNA MINISTERIAL IPV",
    "grupo": "VACUNAS",
    "tipoExamen": 7
  },
  {
    "codPrestacion": "44-04-119-00",
    "nombre": "VACUNA MINISTERIAL MENINGOCOCO ACWY",
    "grupo": "VACUNAS",
    "tipoExamen": 7
  },
  {
    "codPrestacion": "44-04-112-00",
    "nombre": "VACUNA MINISTERIAL MENINGOCOCO B",
    "grupo": "VACUNAS",
    "tipoExamen": 7
  },
  {
    "codPrestacion": "44-04-109-00",
    "nombre": "VACUNA MINISTERIAL NEUMOCOCICA 13 V",
    "grupo": "VACUNAS",
    "tipoExamen": 7
  },
  {
    "codPrestacion": "44-04-113-00",
    "nombre": "VACUNA MINISTERIAL NEUMOCOCICA 23 V",
    "grupo": "VACUNAS",
    "tipoExamen": 7
  },
  {
    "codPrestacion": "44-04-225-01",
    "nombre": "VACUNA MINISTERIAL PNI",
    "grupo": "VACUNAS",
    "tipoExamen": 7
  },
  {
    "codPrestacion": "44-04-111-00",
    "nombre": "VACUNA MINISTERIAL SRP",
    "grupo": "VACUNAS",
    "tipoExamen": 7
  },
  {
    "codPrestacion": "44-04-110-00",
    "nombre": "VACUNA MINISTERIAL VARICELA",
    "grupo": "VACUNAS",
    "tipoExamen": 7
  },
  {
    "codPrestacion": "44-04-105-00",
    "nombre": "VACUNA MINISTERIAL VIRUELA DEL MONO",
    "grupo": "VACUNAS",
    "tipoExamen": 7
  },
  {
    "codPrestacion": "44-04-114-00",
    "nombre": "VACUNA MINISTERIAL VPH TETRA",
    "grupo": "VACUNAS",
    "tipoExamen": 7
  },
  {
    "codPrestacion": "44-04-231-01",
    "nombre": "VACUNA MINISTERIAL VRS 100 MG",
    "grupo": "VACUNAS",
    "tipoExamen": 7
  },
  {
    "codPrestacion": "44-04-231-00",
    "nombre": "VACUNA MINISTERIAL VRS 50 MG",
    "grupo": "VACUNAS",
    "tipoExamen": 7
  },
  {
    "codPrestacion": "44-04-225-05",
    "nombre": "VACUNA MINITERIAL HEPATITIS A ADULTO",
    "grupo": "VACUNAS",
    "tipoExamen": 7
  },
  {
    "codPrestacion": "44-04-120-00",
    "nombre": "VACUNA MINSITERIAL HIB",
    "grupo": "VACUNAS",
    "tipoExamen": 7
  },
  {
    "codPrestacion": "44-04-115-00",
    "nombre": "VACUNA MINSTERIAL VPH NONA",
    "grupo": "VACUNAS",
    "tipoExamen": 7
  },
  {
    "codPrestacion": "44-04-103-00",
    "nombre": "VACUNA NEUMOCOCO 13V (PREVENAR 13)",
    "grupo": "VACUNAS",
    "tipoExamen": 7
  },
  {
    "codPrestacion": "44-04-214-00",
    "nombre": "VACUNA NEUMOCOCO 23V (PNEUMOVAX)",
    "grupo": "VACUNAS",
    "tipoExamen": 7
  },
  {
    "codPrestacion": "44-04-095-00",
    "nombre": "VACUNA ROTAVIRUS (ROTARIX)",
    "grupo": "VACUNAS",
    "tipoExamen": 7
  },
  {
    "codPrestacion": "44-04-200-00",
    "nombre": "VACUNA ROTAVIRUS (ROTATEQ)",
    "grupo": "VACUNAS",
    "tipoExamen": 7
  },
  {
    "codPrestacion": "44-04-123-00",
    "nombre": "VACUNA SOLICITUD ESPECIAL",
    "grupo": "VACUNAS",
    "tipoExamen": 7
  },
  {
    "codPrestacion": "44-04-220-00",
    "nombre": "VACUNA VARICELA (VARIVAX)",
    "grupo": "VACUNAS",
    "tipoExamen": 7
  },
  {
    "codPrestacion": "44-04-124-00",
    "nombre": "VACUNA VIRUS HERPES ZOSTER (SHINGRIX)",
    "grupo": "VACUNAS",
    "tipoExamen": 7
  },
  {
    "codPrestacion": "44-04-104-00",
    "nombre": "VACUNA VPH NONA (GARDASIL 9)",
    "grupo": "VACUNAS",
    "tipoExamen": 7
  },
  {
    "codPrestacion": "44-04-106-00",
    "nombre": "VACUNA VRS ADULTO (AREXVY)",
    "grupo": "VACUNAS",
    "tipoExamen": 7
  },
  {
    "codPrestacion": "44-04-125-00",
    "nombre": "VACUNA VRS BIVALENTE(ABRYSVO)",
    "grupo": "VACUNAS",
    "tipoExamen": 7
  },
  {
    "codPrestacion": "04-04-118-12",
    "nombre": "ECOTOMOGRAFIA DOPPLER LABORATORIO VASCUL",
    "grupo": "VASCULAR",
    "tipoExamen": 7
  },
  {
    "codPrestacion": "17-91-099-01",
    "nombre": "ESCLEROTERAPIA POR MEDICO",
    "grupo": "VASCULAR",
    "tipoExamen": 7
  },
  {
    "codPrestacion": "17-91-099-00",
    "nombre": "MICRO ESCLEROTERAPIA POR EU (INC SALA)",
    "grupo": "VASCULAR",
    "tipoExamen": 7
  },
  {
    "codPrestacion": "17-01-017-00",
    "nombre": "PLETISMOGRAFIA VASCULAR PERIFERICO",
    "grupo": "VASCULAR",
    "tipoExamen": 7
  },
  {
    "codPrestacion": "17-01-018-00",
    "nombre": "REG.ECOARTERIAL O ECOVENOSO PERIF C/U",
    "grupo": "VASCULAR",
    "tipoExamen": 7
  }
]
